<?xml version="1.0" encoding="UTF-8"?>
<faces-config version="1.2" xmlns="http://java.sun.com/xml/ns/javaee"
 xmlns:xi="http://www.w3.org/2001/XInclude"
 xmlns:xsi="http://www.w3.org/2001/XMLSchema-instance" xsi:schemaLocation="http://java.sun.com/xml/ns/javaee http://java.sun.com/xml/ns/javaee/web-facesconfig_1_2.xsd">
  <managed-bean>
  <managed-bean-name>socCtrl</managed-bean-name>
  <managed-bean-class>com.bondeko.sysgeho.ui.ref.controleur.SocCtrl</managed-bean-class>
  <managed-bean-scope>session</managed-bean-scope>
 </managed-bean>
 <managed-bean>
  <managed-bean-name>assCtrl</managed-bean-name>
  <managed-bean-class>com.bondeko.sysgeho.ui.ref.controleur.AssCtrl</managed-bean-class>
  <managed-bean-scope>session</managed-bean-scope>
 </managed-bean>
 <managed-bean>
  <managed-bean-name>typExamCtrl</managed-bean-name>
  <managed-bean-class>com.bondeko.sysgeho.ui.ref.controleur.TypExamCtrl</managed-bean-class>
  <managed-bean-scope>session</managed-bean-scope>
 </managed-bean>
 <managed-bean>
  <managed-bean-name>catExamCtrl</managed-bean-name>
  <managed-bean-class>com.bondeko.sysgeho.ui.ref.controleur.CatExamCtrl</managed-bean-class>
  <managed-bean-scope>session</managed-bean-scope>
 </managed-bean>
 <managed-bean>
  <managed-bean-name>typSoinCtrl</managed-bean-name>
  <managed-bean-class>com.bondeko.sysgeho.ui.ref.controleur.TypSoinCtrl</managed-bean-class>
  <managed-bean-scope>session</managed-bean-scope>
 </managed-bean>
 <managed-bean>
  <managed-bean-name>specCtrl</managed-bean-name>
  <managed-bean-class>com.bondeko.sysgeho.ui.ref.controleur.SpecCtrl</managed-bean-class>
  <managed-bean-scope>session</managed-bean-scope>
 </managed-bean>
 <managed-bean>
  <managed-bean-name>typRdvCtrl</managed-bean-name>
  <managed-bean-class>com.bondeko.sysgeho.ui.ref.controleur.TypRdvCtrl</managed-bean-class>
  <managed-bean-scope>session</managed-bean-scope>
 </managed-bean>
 <navigation-rule>
  <from-view-id>*</from-view-id>
  <navigation-case>
   <from-outcome>SocDetails</from-outcome>
   <to-view-id>/modules/referentiel/pages/SocDetails.xhtml</to-view-id>
  </navigation-case>
  <navigation-case>
   <from-outcome>SocEdition</from-outcome>
   <to-view-id>/modules/referentiel/pages/SocEdition.xhtml</to-view-id>
   <redirect/>
  </navigation-case>
  <navigation-case>
   <from-outcome>SocListe</from-outcome>
   <to-view-id>/modules/referentiel/pages/SocListe.xhtml</to-view-id>
   <redirect/>
  </navigation-case>
  <navigation-case>
   <from-outcome>AssDetails</from-outcome>
   <to-view-id>/modules/referentiel/pages/AssDetails.xhtml</to-view-id>
  </navigation-case>
  <navigation-case>
   <from-outcome>AssEdition</from-outcome>
   <to-view-id>/modules/referentiel/pages/AssEdition.xhtml</to-view-id>
   <redirect/>
  </navigation-case>
  <navigation-case>
   <from-outcome>AssListe</from-outcome>
   <to-view-id>/modules/referentiel/pages/AssListe.xhtml</to-view-id>
   <redirect/>
  </navigation-case>
  <navigation-case>
   <from-outcome>CatExamDetails</from-outcome>
   <to-view-id>/modules/referentiel/pages/CatExamDetails.xhtml</to-view-id>
  </navigation-case>
  <navigation-case>
   <from-outcome>CatExamEdition</from-outcome>
   <to-view-id>/modules/referentiel/pages/CatExamEdition.xhtml</to-view-id>
   <redirect/>
  </navigation-case>
  <navigation-case>
   <from-outcome>CatExamListe</from-outcome>
   <to-view-id>/modules/referentiel/pages/CatExamListe.xhtml</to-view-id>
   <redirect/>
  </navigation-case>
  <navigation-case>
   <from-outcome>TypExamDetails</from-outcome>
   <to-view-id>/modules/referentiel/pages/TypExamDetails.xhtml</to-view-id>
  </navigation-case>
  <navigation-case>
   <from-outcome>TypExamEdition</from-outcome>
   <to-view-id>/modules/referentiel/pages/TypExamEdition.xhtml</to-view-id>
   <redirect/>
  </navigation-case>
  <navigation-case>
   <from-outcome>TypExamListe</from-outcome>
   <to-view-id>/modules/referentiel/pages/TypExamListe.xhtml</to-view-id>
   <redirect/>
  </navigation-case>
  
  <navigation-case>
   <from-outcome>TypSoinDetails</from-outcome>
   <to-view-id>/modules/referentiel/pages/TypSoinDetails.xhtml</to-view-id>
  </navigation-case>
  <navigation-case>
   <from-outcome>TypSoinEdition</from-outcome>
   <to-view-id>/modules/referentiel/pages/TypSoinEdition.xhtml</to-view-id>
   <redirect/>
  </navigation-case>
  <navigation-case>
   <from-outcome>TypSoinListe</from-outcome>
   <to-view-id>/modules/referentiel/pages/TypSoinListe.xhtml</to-view-id>
   <redirect/>
  </navigation-case>
  
  <navigation-case>
   <from-outcome>SpecDetails</from-outcome>
   <to-view-id>/modules/referentiel/pages/SpecDetails.xhtml</to-view-id>
  </navigation-case>
  <navigation-case>
   <from-outcome>SpecEdition</from-outcome>
   <to-view-id>/modules/referentiel/pages/SpecEdition.xhtml</to-view-id>
   <redirect/>
  </navigation-case>
  <navigation-case>
   <from-outcome>SpecListe</from-outcome>
   <to-view-id>/modules/referentiel/pages/SpecListe.xhtml</to-view-id>
   <redirect/>
  </navigation-case>
  
  <navigation-case>
   <from-outcome>TypRdvDetails</from-outcome>
   <to-view-id>/modules/referentiel/pages/TypRdvDetails.xhtml</to-view-id>
  </navigation-case>
  <navigation-case>
   <from-outcome>TypRdvEdition</from-outcome>
   <to-view-id>/modules/referentiel/pages/TypRdvEdition.xhtml</to-view-id>
   <redirect/>
  </navigation-case>
  <navigation-case>
   <from-outcome>TypRdvListe</from-outcome>
   <to-view-id>/modules/referentiel/pages/TypRdvListe.xhtml</to-view-id>
   <redirect/>
  </navigation-case>
  
  
 </navigation-rule>
</faces-config>
